MANIFEST.in
setup.py
pyarmor_runtime_000000/__init__.py
pyarmor_runtime_000000/pyarmor_runtime
pyarmor_runtime_000000/pyarmor_runtime.pyd
pyarmor_runtime_000000/__pycache__/__init__.cpython-311.pyc
tohoku_tus_IoT_automation.egg-info/PKG-INFO
tohoku_tus_IoT_automation.egg-info/SOURCES.txt
tohoku_tus_IoT_automation.egg-info/dependency_links.txt
tohoku_tus_IoT_automation.egg-info/requires.txt
tohoku_tus_IoT_automation.egg-info/top_level.txt