Metadata-Version: 2.1
Name: tohoku-tus-IoT-automation
Version: 0.3.3
Summary: Energy monitoring management interface for student IoT projects developed during collaboration between the renewable energy 3rd year groups from Ireland and Japan. アイルランドと日本の再生可能エネルギーの 3 年生グループが協力して開発した、学生プロジェクトのためのエネルギー監視管理インターフェイス。
Author: K00000993
Author-email: K00000993zx@grpstudentiot.tohoku.ac.jp
Classifier: Programming Language :: Python :: 3
Classifier: License :: OSI Approved :: MIT License
Classifier: Operating System :: Microsoft :: Windows
Requires-Python: >=3.6
